youtube3/__init__.py
youtube3/authenticate.py
youtube3/common.py
youtube3/exceptions.py
youtube3/settings.py
youtube3/youtube_client.py
youtube3-1.2.4.dist-info/METADATA
youtube3-1.2.4.dist-info/WHEEL
youtube3-1.2.4.dist-info/top_level.txt
youtube3-1.2.4.dist-info/RECORD
