Metadata-Version: 2.1
Name: youtube3
Version: 1.2.4
Summary: Python Youtube v3 API Wrapper
Home-page: https://github.com/diegoami/youtube3/
Author: Diego Amicabile
Author-email: diego.amicabile@gmail.com
License: BSD License
Keywords: youtube wrapper oauth2 v3
Classifier: Environment :: Web Environment
Classifier: Intended Audience :: Developers
Classifier: License :: OSI Approved :: BSD License
Classifier: Operating System :: OS Independent
Classifier: Programming Language :: Python
Classifier: Programming Language :: Python :: 3
Classifier: Topic :: Internet :: WWW/HTTP
Classifier: Topic :: Internet :: WWW/HTTP :: Dynamic Content
Classifier: Topic :: Internet :: WWW/HTTP :: HTTP Servers
Requires-Dist: google-api-python-client
Requires-Dist: oauth2client
